chainctl_auth_tox/__init__.py
chainctl_auth_tox/bootstrap.py
keyrings/__init__.py
keyrings/chainctl_auth.py
keyrings_chainguard_libraries-0.2.0.dist-info/METADATA
keyrings_chainguard_libraries-0.2.0.dist-info/WHEEL
keyrings_chainguard_libraries-0.2.0.dist-info/entry_points.txt
keyrings_chainguard_libraries-0.2.0.dist-info/licenses/LICENSE
keyrings_chainguard_libraries-0.2.0.dist-info/RECORD
