Metadata-Version: 2.4
Name: keyrings-chainguard-libraries
Version: 0.2.0
Summary: Chainctl keyring backend for Python package authentication
Project-URL: Homepage, https://github.com/chainguard-dev/keyrings-chainguard-libraries
Author-email: Ajay Kemparaj <ajay.kemparaj@chainguard.dev>
License-Expression: Apache-2.0
License-File: LICENSE
Classifier: Development Status :: 4 - Beta
Classifier: Intended Audience :: Developers
Classifier: License :: OSI Approved :: Apache Software License
Classifier: Programming Language :: Python :: 3
Classifier: Programming Language :: Python :: 3.9
Classifier: Programming Language :: Python :: 3.10
Classifier: Programming Language :: Python :: 3.11
Classifier: Programming Language :: Python :: 3.12
Classifier: Programming Language :: Python :: 3.13
Classifier: Topic :: Software Development :: Libraries :: Python Modules
Classifier: Topic :: System :: Archiving :: Packaging
Requires-Python: >=3.9
Requires-Dist: keyring>=15.1
Requires-Dist: pluggy>=0.12.0
Provides-Extra: dev
Requires-Dist: black; extra == 'dev'
Requires-Dist: build; extra == 'dev'
Requires-Dist: flake8; extra == 'dev'
Requires-Dist: mypy; extra == 'dev'
Requires-Dist: pytest-cov; extra == 'dev'
Requires-Dist: pytest-mock; extra == 'dev'
Requires-Dist: pytest-timeout; extra == 'dev'
Requires-Dist: pytest>=6.0; extra == 'dev'
Requires-Dist: ruff; extra == 'dev'
Requires-Dist: twine; extra == 'dev'
Provides-Extra: testing
Requires-Dist: pytest-cov; extra == 'testing'
Requires-Dist: pytest-mock; extra == 'testing'
Requires-Dist: pytest-timeout; extra == 'testing'
Requires-Dist: pytest>=6.0; extra == 'testing'
